heart_centered_prompts/__init__.py
heart_centered_prompts/api.py
heart_centered_prompts/prompts/__init__.py
heart_centered_prompts/prompts/align_to_love/comprehensive.txt
heart_centered_prompts/prompts/align_to_love/concise.txt
heart_centered_prompts/prompts/align_to_love/standard.txt
heart_centered_prompts/prompts/align_to_love/terse.txt
tests/__init__.py
tests/test_get_prompt.py
heart_centered_prompts-0.1.12.dist-info/METADATA
heart_centered_prompts-0.1.12.dist-info/WHEEL
heart_centered_prompts-0.1.12.dist-info/top_level.txt
heart_centered_prompts-0.1.12.dist-info/RECORD
