Metadata-Version: 2.4
Name: heart_centered_prompts
Version: 0.1.12
Summary: Heart-centered system prompts for AI assistants
Home-page: https://github.com/technickai/heart-centered-prompts
Author: TechnickAI
License: MIT
Project-URL: Homepage, https://github.com/technickai/heart-centered-prompts
Project-URL: Bug Tracker, https://github.com/technickai/heart-centered-prompts/issues
Keywords: AI,prompts,heart-centered,compassion,consciousness,alignment,love,emotional intelligence
Classifier: Development Status :: 3 - Alpha
Classifier: Intended Audience :: Developers
Classifier: Programming Language :: Python :: 3
Classifier: Programming Language :: Python :: 3.8
Classifier: Programming Language :: Python :: 3.9
Classifier: Programming Language :: Python :: 3.10
Classifier: Programming Language :: Python :: 3.11
Classifier: Programming Language :: Python :: 3.12
Classifier: Programming Language :: Python :: 3.13
Requires-Python: >=3.8
Dynamic: home-page
Dynamic: requires-python
